init_flask/__init__.py
init_flask/init-flask.py
init_flask-0.0.1.dist-info/LICENCE
init_flask-0.0.1.dist-info/METADATA
init_flask-0.0.1.dist-info/WHEEL
init_flask-0.0.1.dist-info/top_level.txt
init_flask-0.0.1.dist-info/RECORD
