Metadata-Version: 2.1
Name: init-flask
Version: 0.0.1
Summary: A python package to easily setup a flak development environment
Author-email: Sam <samuelayodeji2478@gmail.com>
Project-URL: Homepage, https://github.com/olascoWorks/init-flask
Project-URL: Issues, https://github.com/olascoWorks/init-flask/issues
Classifier: Programming Language :: Python :: 3
Classifier: License :: OSI Approved :: MIT License
Classifier: Operating System :: OS Independent
Requires-Python: >=3.8
License-File: LICENCE
Requires-Dist: click
Requires-Dist: requests
